traefik_validator/__init__.py
traefik_validator/settings.py
traefik_validator/tests.py
traefik_validator/utils.py
traefik_validator-0.1.1.dist-info/LICENSE
traefik_validator-0.1.1.dist-info/METADATA
traefik_validator-0.1.1.dist-info/WHEEL
traefik_validator-0.1.1.dist-info/entry_points.txt
traefik_validator-0.1.1.dist-info/top_level.txt
traefik_validator-0.1.1.dist-info/RECORD
