Metadata-Version: 2.1
Name: traefik-validator
Version: 0.1.1
Summary: validate_traefik command for validating user traefik config file.
Home-page: https://github.com/aminiun/traefik-validator
Author: Amin Aminian
Author-email: a.aminian321@gmail.com
License: BSD-3-Clause
Classifier: Environment :: Web Environment
Classifier: Intended Audience :: Developers
Classifier: License :: OSI Approved :: BSD License
Classifier: Operating System :: OS Independent
Classifier: Programming Language :: Python :: 3 :: Only
Classifier: Topic :: Software Development :: Libraries :: Application Frameworks
Classifier: Topic :: Software Development :: Libraries :: Python Modules
Requires-Python: >=3.6
License-File: LICENSE
